{
    "id": "20250205222840_39",
    "name": "Bean Me Up",
    "star": "4.4",
    "number": "4113",
    "score": "18097.2",
    "area": "Anjuna",
    "url": "https://www.google.com/maps/place/Bean+Me+Up/@15.5961055,73.7482125,17z/data=!3m1!4b1!4m9!3m8!1s0x3bbfe983f642d3df:0x4a6bf50d7db9738c!5m2!4m1!1i2!8m2!3d15.5961055!4d73.7482125!16s%2Fg%2F11r8sr1hh?authuser=0&hl=en&entry=ttu&g_ep=EgoyMDI1MDIwMi4wIKXMDSoASAFQAw%3D%3D",
    "restaurant_image": "https://lh5.googleusercontent.com/p/AF1QipMwUfG83skBGzCS1iF_CeL5cnXS7ArwYoOpsIAs=w427-h240-k-no",
    "tags": [],
    "reviews": []
}